<?xml version="1.0" encoding="utf-8" ?>
<odoo>
    <template id="assets_backend" inherit_id="web.assets_backend">
        <xpath expr="." position="inside">
            <link
                rel="stylesheet"
                href="/helpdesk_mgmt_pms/static/src/scss/helpdesk_mgmt_pms.scss"
            />
            <script
                type="text/javascript"
                src="/helpdesk_mgmt_pms/static/src/js/helpdesk_mgmt_pms.js"
            />
        </xpath>
    </template>
    <!-- View Ticket kanban -->
    <record id="helpdesk_ticket_view_search" model="ir.ui.view">
        <field name="name">helpdesk.ticket.view.search</field>
        <field name="model">helpdesk.ticket</field>
        <field name="inherit_id" ref="helpdesk_mgmt.helpdesk_ticket_view_search" />
        <field name="arch" type="xml">
            <xpath expr="//field[@name='name']" position="after">
                <field name="company_id" />
                <field name="property_id" />
                <field name="room_id" />
            </xpath>
            <xpath expr="//filter[@name='group_partner']" position="after">
                <filter
                    string="Company"
                    name="group_company"
                    domain="[]"
                    context="{'group_by':'company_id'}"
                />
                <filter
                    string="Property"
                    name="group_property"
                    domain="[]"
                    context="{'group_by':'property_id'}"
                />
                <filter
                    string="Room"
                    name="group_room"
                    domain="[]"
                    context="{'group_by':'room_id'}"
                />
            </xpath>
        </field>
    </record>
    <!-- View Ticket Tree -->
    <record id="ticket_view_tree" model="ir.ui.view">
        <field name="model">helpdesk.ticket</field>
        <field name="inherit_id" ref="helpdesk_mgmt.ticket_view_tree" />
        <field name="arch" type="xml">
            <xpath expr="//field[@name='number']" position="after">
                <field name="company_id" />
                <field name="property_id" />
                <field name="room_id" />
            </xpath>
        </field>
    </record>
    <!-- View Form Ticket -->
    <record id="ticket_view_form" model="ir.ui.view">
        <field name="model">helpdesk.ticket</field>
        <field name="inherit_id" ref="helpdesk_mgmt.ticket_view_form" />
        <field name="arch" type="xml">
            <xpath expr="//field[@name='priority']" position="after">
                <field
                    name="company_id"
                    options="{'no_create': True}"
                    groups="base.group_multi_company"
                />
                <field name="property_id" options="{'no_create': True}" />
                <field
                    name="room_id"
                    options="{'no_create': True}"
                    attrs="{'invisible': [('property_id', '=', False)]}"
                />
            </xpath>
        </field>
    </record>
</odoo>
